libname/__init__.py
libname/approximators.py
libname/intergrators.py
rootdescent-0.1.0.dist-info/LICENSE
rootdescent-0.1.0.dist-info/METADATA
rootdescent-0.1.0.dist-info/WHEEL
rootdescent-0.1.0.dist-info/top_level.txt
rootdescent-0.1.0.dist-info/RECORD
