Metadata-Version: 2.1
Name: rootdescent
Version: 0.1.0
Summary: A package for approximating roots using various methods.
Home-page: https://github.com/tshepomk/rootdescent
Author: Tshepo Moagi
Author-email: tshepo.k.moagi@gmail.com
License: UNKNOWN
Platform: UNKNOWN
Classifier: Development Status :: 3 - Alpha
Classifier: Intended Audience :: Education
Classifier: License :: OSI Approved :: MIT License
Classifier: Operating System :: OS Independent
Classifier: Programming Language :: Python :: 3
Classifier: Programming Language :: Python :: 3.6
Requires-Python: >=3.6
License-File: LICENSE
